TradingBot/__init__.py
TradingBot/main.py
TradingBot/strategy/__init__.py
TradingBot/strategy/__main__.py
TradingBot/strategy/arron.py
TradingBot/strategy/backtest.py
TradingBot/strategy/computation.py
TradingBot/strategy/double_momentum.py
TradingBot/strategy/momentum.py
TradingBot/utils/__init__.py
TradingBot/utils/data.py
TradingBot/utils/emailme.py
TradingBot/utils/tradebot.py
TradingBot-0.1.0.dist-info/METADATA
TradingBot-0.1.0.dist-info/WHEEL
TradingBot-0.1.0.dist-info/top_level.txt
TradingBot-0.1.0.dist-info/RECORD
