Metadata-Version: 2.1
Name: TradingBot
Version: 0.1.0
Summary: A Python toolkit for strategy design, backtesting, and algorithm trading
Home-page: https://github.com/dayuyang1999/TradingBot
Download-URL: https://pypi.org/project/TradingBot
Author: Dayu Yang
Author-email: dayu@udel.edu
License: MIT
Keywords: Stock,Trading
Requires-Dist: alpaca-trade-api (<3.0.0,>=2.0.0)
Requires-Dist: jupyter
